{
    "data": [{
        "id": 4671917,
        "action_type": "Like",
        "action": {
            "id": 7163,
            "user_id": 8532,
            "item_id": 402531,
            "deleted_at": null,
            "created_at": "2014-04-01T22:05:20.683Z",
            "updated_at": "2014-04-01T22:05:20.683Z"
        },
        "created_at": "2014-03-13T17:01:38.370Z",
        "subject_type": "Item",
        "subject": {
            "id": 402531,
            "description": "Voluptatem dolores beatae id labore ut corporis tempora id numquam in vel et nemo sed natus quos provident commodi quia quo officiis distinctio qui aut non iure nam illum reprehenderit debitis hic et esse molestiae nulla eaque excepturi quaerat eveniet nisi asperiores voluptate.",
            "creator_id": 1,
            "updated_at": "2014-03-13T17:01:37.955Z",
            "created_at": "2014-03-13T17:01:37.955Z",
            "nonce": null,
            "photos": {
                "_50x50": "https://morsel-staging.s3.amazonaws.com/item-images/item/40253l/_50x50_648922f4-8850-4402-8ff8-8ffc1e2f8c01.png",
                "_80x80": "https://morsel-staging.s3.amazonaws.com/item-images/item/40253l/_80x80_648922f4-8850-4402-8ff8-8ffc1e2f8c01.png",
                "_100x100": "https://morsel-staging.s3.amazonaws.com/item-images/item/40253l/_100x100_648922f4-8850-4402-8ff8-8ffc1e2f8c01.png",
                "_240x240": "https://morsel-staging.s3.amazonaws.com/item-images/item/40253l/_240x240_648922f4-8850-4402-8ff8-8ffc1e2f8c01.png",
                "_320x320": "https://morsel-staging.s3.amazonaws.com/item-images/item/40253l/_320x320_648922f4-8850-4402-8ff8-8ffc1e2f8c01.png",
                "_480x480": "https://morsel-staging.s3.amazonaws.com/item-images/item/40253l/_480x480_648922f4-8850-4402-8ff8-8ffc1e2f8c01.png",
                "_640x640": "https://morsel-staging.s3.amazonaws.com/item-images/item/40253l/_640x640_648922f4-8850-4402-8ff8-8ffc1e2f8c01.png",
                "_992x992": "https://morsel-staging.s3.amazonaws.com/item-images/item/40253l/_992x992_648922f4-8850-4402-8ff8-8ffc1e2f8c01.png"
            },
            "photo_processing": false,
            "morsel_id": 8057,
            "sort_order": 2,
            "url": "https://test.eatmorsel.com/turdferg/8057-some-morsel/2",
            "liked": true
        },
        "creator": {
            "id": 8532,
            "username": "turdferg",
            "first_name": "Turd",
            "last_name": "Ferguson",
            "created_at": "2014-03-13T17:01:38.219Z",
            "bio": "Suck it, Trebek!",
            "photos": {
                "_40x40": "https://morsel-staging.s3.amazonaws.com/user-images/user/8532/1389119757-batman.jpeg",
                "_72x72": "https://morsel-staging.s3.amazonaws.com/user-images/user/8532/1389119757-batman.jpeg",
                "_80x80": "https://morsel-staging.s3.amazonaws.com/user-images/user/8532/1389119757-batman.jpeg",
                "_144x144": "https://morsel-staging.s3.amazonaws.com/user-images/user/8532/1389119757-batman.jpeg"
            },
            "photo_processing": null
        }
    }]
}
